xmacro/__init__.py
xmacro/common.sdf.xmacro
xmacro/common.urdf.xmacro
xmacro/xmacro.py
xmacro/xmacro4sdf.py
xmacro/xmacro4urdf.py
xmacro/xml_format.py
xmacro-1.2.0.dist-info/LICENSE
xmacro-1.2.0.dist-info/METADATA
xmacro-1.2.0.dist-info/WHEEL
xmacro-1.2.0.dist-info/entry_points.txt
xmacro-1.2.0.dist-info/top_level.txt
xmacro-1.2.0.dist-info/RECORD
