Metadata-Version: 2.1
Name: xmacro
Version: 1.2.0
Summary: a simple XML macro tool
Home-page: https://github.com/gezp/xmacro
Author: Zhenpeng Ge
Author-email: zhenpeng.ge@qq.com
License: MIT
Keywords: xml,macro,xacro,xmacro,sdformat,sdf,urdf
Platform: UNKNOWN
License-File: LICENSE
